inventree_zebra/__init__.py
inventree_zebra/request_wrappers.py
inventree_zebra/server.py
inventree_zebra/version.py
inventree_zebra/zebra_plugin.py
inventree_zebra/static/ui_settings.js
inventree_zebra_plugin-0.9.0.dist-info/licenses/LICENSE
inventree_zebra_plugin-0.9.0.dist-info/METADATA
inventree_zebra_plugin-0.9.0.dist-info/WHEEL
inventree_zebra_plugin-0.9.0.dist-info/entry_points.txt
inventree_zebra_plugin-0.9.0.dist-info/top_level.txt
inventree_zebra_plugin-0.9.0.dist-info/RECORD
