Metadata-Version: 2.4
Name: inventree-zebra-plugin
Version: 0.9.0
Summary: Zebra label printer plugin for InvenTree
Home-page: https://github.com/SergeoLacruz/inventree-zebra-plugin
Author: Michael Buchmann
Author-email: michael@buchmann.ruhr
License: MIT
Keywords: inventree label printer printing inventory
Classifier: Programming Language :: Python :: 3
Classifier: Operating System :: OS Independent
Classifier: Framework :: InvenTree
Requires-Python: >=3.6
License-File: LICENSE
Requires-Dist: zpl>=0.1.11
Dynamic: author
Dynamic: author-email
Dynamic: classifier
Dynamic: description
Dynamic: description-content-type
Dynamic: home-page
Dynamic: keywords
Dynamic: license
Dynamic: license-file
Dynamic: requires-dist
Dynamic: requires-python
Dynamic: summary
